MANIFEST.in
README.md
setup.py
mobio_cli/__init__.py
mobio_cli/__main__.py
mobio_cli.egg-info/PKG-INFO
mobio_cli.egg-info/SOURCES.txt
mobio_cli.egg-info/dependency_links.txt
mobio_cli.egg-info/entry_points.txt
mobio_cli.egg-info/top_level.txt
mobio_cli/templates/Dockerfile
mobio_cli/templates/Dockerfile-release
mobio_cli/templates/README.md
mobio_cli/templates/app_{#PROJECT_NAME_SNAKE_LOWERCASE#}_api.{pymobio}
mobio_cli/templates/check_image.sh
mobio_cli/templates/k8s-Jenkinsfile
mobio_cli/templates/prepare_env.sh
mobio_cli/templates/requirements.txt
mobio_cli/templates/script-update-version.sh
mobio_cli/templates/startup.sh
mobio_cli/templates/test.env
mobio_cli/templates/configs/__init__.{pymobio}
mobio_cli/templates/resources/configs/{#PROJECT_NAME_SNAKE_LOWERCASE#}.conf
mobio_cli/templates/resources/lang/message_en.json
mobio_cli/templates/resources/lang/message_vi.json
mobio_cli/templates/src/__init__.{pymobio}
mobio_cli/templates/src/apis/__init__.{pymobio}
mobio_cli/templates/src/apis/v1_0/__init__.{pymobio}
mobio_cli/templates/src/apis/v1_0/blueprints_api.{pymobio}
mobio_cli/templates/src/common/__init__.{pymobio}
mobio_cli/templates/src/controllers/example_controller.{pymobio}
mobio_cli/templates/yaml/BASE/0_script_init_deploy.yaml
mobio_cli/templates/yaml/BASE/deploy_{#PROJECT_NAME_SNAKE_LOWERCASE#}_app_api.yaml