Metadata-Version: 2.1
Name: mobio-cli
Version: 1.0.6
Summary: Command line create Mobio's projects
Home-page: UNKNOWN
Author: MOBIO
Author-email: contact@mobio.vn
License: UNKNOWN
Platform: UNKNOWN
Classifier: Programming Language :: Python
Classifier: Programming Language :: Python :: 3.8
Classifier: Programming Language :: Python :: 3.9
